[
  {
    "name": "FABERGE",
    "minor": []
  },
  {
    "name": "COLOSSUS",
    "minor": [
      "HULKING",
      "ANCIENT",
      "BRASS",
      "CLOCKWORK",
      "RELICT",
      "STRIDING",
      "REVENANT",
      "TRIUMPHANT",
      "BURNING",
      "PRINCELY",
      "ORACULAR",
      "NEW",
      "THIRTEENTH"
    ]
  },
  {
    "name": "CROWN",
    "minor": [
      "WHALEBONE",
      "FILIGRANE",
      "GRAVEN",
      "OBSIDIONAL",
      "FULIGIN",
      "MURAL",
      "BLOCKADE",
      "CIVIC",
      "SIEGE",
      "LORDLY",
      "BLACKSTONE"
    ]
  }
]
